{
  "cli": {
    "version": ">= 3.15.1",
    "appVersionSource": "remote"
  },
  "build": {
    "development": {
      "env": {
        "EAS_ENV": "development"
      },
      "channel": "dev",
      "distribution": "internal",
      "autoIncrement": true,
      "developmentClient": true,
      "ios": {
        "simulator": true
      }
    },
    "test": {
      "env": {
        "EAS_ENV": "test"
      },
      "channel": "test",
      "autoIncrement": true,
      "distribution": "internal",
      "developmentClient": true
    },
    "production": {
      "autoIncrement": true,
      "channel": "production",
      "env": {
        "EAS_ENV": "production"
      }
    }
  },
  "submit": {
    "production": {
      "ios": {
        "appleId": "hirdman.alex@icloud.com",
        "appleTeamId": "64FFA8NJWP"
      }
    }
  }
}
